mifflin/__init__.py
mifflin/__main__.py
mifflin/config.txt
mifflin-0.1.1.dist-info/METADATA
mifflin-0.1.1.dist-info/WHEEL
mifflin-0.1.1.dist-info/entry_points.txt
mifflin-0.1.1.dist-info/top_level.txt
mifflin-0.1.1.dist-info/RECORD
